setup.py
Int/Int.py
Int/__init__.py
Ir_calculator.egg-info/PKG-INFO
Ir_calculator.egg-info/SOURCES.txt
Ir_calculator.egg-info/dependency_links.txt
Ir_calculator.egg-info/not-zip-safe
Ir_calculator.egg-info/requires.txt
Ir_calculator.egg-info/top_level.txt