Metadata-Version: 2.1
Name: Ir-calculator
Version: 0.3
Summary: Calculate Criminla IR
Home-page: UNKNOWN
Author: Jay Jo
License: UNKNOWN
Platform: UNKNOWN
